{"nodes": [{"id": "docs_adr_adr_backlog_adr_backlog", "label": "ADR Backlog for BodyLife CRM", "file_type": "document", "source_file": "docs/adr/adr-backlog.md", "source_location": null, "source_url": null, "captured_at": null, "author": null, "contributor": null}, {"id": "docs_adr_adr_backlog_blocking_decisions", "label": "Blocking Decisions Before Implementation", "file_type": "concept", "source_file": "docs/adr/adr-backlog.md", "source_location": null, "source_url": null, "captured_at": null, "author": null, "contributor": null}, {"id": "docs_adr_adr_backlog_deferred_decisions", "label": "Deferred Decisions", "file_type": "concept", "source_file": "docs/adr/adr-backlog.md", "source_location": null, "source_url": null, "captured_at": null, "author": null, "contributor": null}, {"id": "docs_adr_adr_backlog_vertical_slice_prototype", "label": "Vertical Slice Prototype", "file_type": "concept", "source_file": "docs/adr/adr-backlog.md", "source_location": null, "source_url": null, "captured_at": null, "author": null, "contributor": null}, {"id": "docs_adr_adr_backlog", "label": "docs/adr/adr-backlog.md", "file_type": "document", "source_file": "docs/adr/adr-backlog.md", "source_location": null, "source_url": null, "captured_at": null, "author": null, "contributor": null}, {"id": "docs_adr_adr_backlog_adr_backlog_bodylife_crm", "label": "ADR backlog \u0434\u043b\u044f BodyLife CRM", "file_type": "document", "source_file": "docs/adr/adr-backlog.md", "source_location": "L1", "source_url": null, "captured_at": null, "author": null, "contributor": null}, {"id": "docs_adr_adr_backlog_section", "label": "\u041f\u0440\u0438\u0437\u043d\u0430\u0447\u0435\u043d\u043d\u044f", "file_type": "document", "source_file": "docs/adr/adr-backlog.md", "source_location": "L7", "source_url": null, "captured_at": null, "author": null, "contributor": null}, {"id": "docs_adr_adr_backlog_section_2", "label": "\u0420\u0456\u0448\u0435\u043d\u043d\u044f, \u044f\u043a\u0456 \u0431\u043b\u043e\u043a\u0443\u044e\u0442\u044c \u043f\u043e\u0447\u0430\u0442\u043e\u043a \u0440\u0435\u0430\u043b\u0456\u0437\u0430\u0446\u0456\u0457", "file_type": "document", "source_file": "docs/adr/adr-backlog.md", "source_location": "L13", "source_url": null, "captured_at": null, "author": null, "contributor": null}, {"id": "docs_adr_adr_backlog_section_3", "label": "\u0420\u0456\u0448\u0435\u043d\u043d\u044f, \u044f\u043a\u0456 \u043c\u043e\u0436\u043d\u0430 \u0432\u0456\u0434\u043a\u043b\u0430\u0441\u0442\u0438", "file_type": "document", "source_file": "docs/adr/adr-backlog.md", "source_location": "L26", "source_url": null, "captured_at": null, "author": null, "contributor": null}, {"id": "docs_adr_adr_backlog_vertical_slice_prototype_2", "label": "\u0420\u0456\u0448\u0435\u043d\u043d\u044f \u0434\u043b\u044f vertical slice prototype", "file_type": "document", "source_file": "docs/adr/adr-backlog.md", "source_location": "L35", "source_url": null, "captured_at": null, "author": null, "contributor": null}, {"id": "docs_adr_adr_backlog_adr_001_product_shape_v1", "label": "ADR-001. Product Shape \u0406 \u041e\u043f\u0435\u0440\u0430\u0446\u0456\u0439\u043d\u0430 \u041c\u043e\u0434\u0435\u043b\u044c V1", "file_type": "document", "source_file": "docs/adr/adr-backlog.md", "source_location": "L45", "source_url": null, "captured_at": null, "author": null, "contributor": null}, {"id": "docs_adr_adr_backlog_adr_002_application_architecture", "label": "ADR-002. Application Architecture \u0406 \u041c\u0435\u0436\u0456 \u0417\u0430\u0441\u0442\u043e\u0441\u0443\u043d\u043a\u0443", "file_type": "document", "source_file": "docs/adr/adr-backlog.md", "source_location": "L82", "source_url": null, "captured_at": null, "author": null, "contributor": null}, {"id": "docs_adr_adr_backlog_adr_003_ui_rendering_and_interaction_model", "label": "ADR-003. UI Rendering And Interaction Model", "file_type": "document", "source_file": "docs/adr/adr-backlog.md", "source_location": "L128", "source_url": null, "captured_at": null, "author": null, "contributor": null}, {"id": "docs_adr_adr_backlog_adr_004_module_boundaries_ownership", "label": "ADR-004. Module Boundaries \u0406 Ownership \u0411\u0456\u0437\u043d\u0435\u0441-\u041f\u0440\u0430\u0432\u0438\u043b", "file_type": "document", "source_file": "docs/adr/adr-backlog.md", "source_location": "L171", "source_url": null, "captured_at": null, "author": null, "contributor": null}, {"id": "docs_adr_adr_backlog_adr_005_membership_invariants", "label": "ADR-005. Membership Invariants \u0406 \u041f\u0440\u0430\u0432\u0438\u043b\u0430 \u041f\u0435\u0440\u0435\u0440\u0430\u0445\u0443\u043d\u043a\u0443", "file_type": "document", "source_file": "docs/adr/adr-backlog.md", "source_location": "L239", "source_url": null, "captured_at": null, "author": null, "contributor": null}, {"id": "docs_adr_adr_backlog_adr_006_business_audit_corrections_technical_logs", "label": "ADR-006. Business Audit, Corrections \u0406 Technical Logs", "file_type": "document", "source_file": "docs/adr/adr-backlog.md", "source_location": "L287", "source_url": null, "captured_at": null, "author": null, "contributor": null}, {"id": "docs_adr_adr_backlog_adr_007_reporting_model_consistency_rules", "label": "ADR-007. Reporting Model \u0406 Consistency Rules", "file_type": "document", "source_file": "docs/adr/adr-backlog.md", "source_location": "L334", "source_url": null, "captured_at": null, "author": null, "contributor": null}, {"id": "docs_adr_adr_backlog_adr_008_search_identity_card_rules_duplicate_warnings", "label": "ADR-008. Search Identity, Card Rules \u0406 Duplicate Warnings", "file_type": "document", "source_file": "docs/adr/adr-backlog.md", "source_location": "L397", "source_url": null, "captured_at": null, "author": null, "contributor": null}, {"id": "docs_adr_adr_backlog_adr_009_backup_restore_operational_recovery", "label": "ADR-009. Backup, Restore \u0406 Operational Recovery", "file_type": "document", "source_file": "docs/adr/adr-backlog.md", "source_location": "L465", "source_url": null, "captured_at": null, "author": null, "contributor": null}, {"id": "docs_adr_adr_backlog_adr_010_migration_manual_backfill_paper_fallback_entries", "label": "ADR-010. Migration, Manual Backfill \u0406 Paper Fallback Entries", "file_type": "document", "source_file": "docs/adr/adr-backlog.md", "source_location": "L523", "source_url": null, "captured_at": null, "author": null, "contributor": null}, {"id": "docs_adr_adr_backlog_adr_011_membership_type_lifecycle", "label": "ADR-011. Membership Type Lifecycle", "file_type": "document", "source_file": "docs/adr/adr-backlog.md", "source_location": "L577", "source_url": null, "captured_at": null, "author": null, "contributor": null}, {"id": "docs_adr_adr_backlog_adr_012_permissions_matrix_session_accountability", "label": "ADR-012. Permissions Matrix, Session Accountability \u0406 \u041c\u0435\u0436\u0456 \u0412\u0438\u043f\u0440\u0430\u0432\u043b\u0435\u043d\u044c", "file_type": "document", "source_file": "docs/adr/adr-backlog.md", "source_location": "L636", "source_url": null, "captured_at": null, "author": null, "contributor": null}, {"id": "docs_adr_adr_backlog_adr_013_future_client_self_service_boundary", "label": "ADR-013. Future Client Self-Service Boundary", "file_type": "document", "source_file": "docs/adr/adr-backlog.md", "source_location": "L692", "source_url": null, "captured_at": null, "author": null, "contributor": null}, {"id": "docs_adr_adr_backlog_section_4", "label": "\u0420\u0435\u043a\u043e\u043c\u0435\u043d\u0434\u043e\u0432\u0430\u043d\u0438\u0439 \u043f\u043e\u0440\u044f\u0434\u043e\u043a \u043e\u043f\u0440\u0430\u0446\u044e\u0432\u0430\u043d\u043d\u044f", "file_type": "document", "source_file": "docs/adr/adr-backlog.md", "source_location": "L762", "source_url": null, "captured_at": null, "author": null, "contributor": null}, {"id": "docs_adr_adr_backlog_vertical_slice_adr", "label": "\u041c\u0456\u043d\u0456\u043c\u0430\u043b\u044c\u043d\u0438\u0439 vertical slice \u0434\u043b\u044f \u043f\u0435\u0440\u0435\u0432\u0456\u0440\u043a\u0438 ADR", "file_type": "document", "source_file": "docs/adr/adr-backlog.md", "source_location": "L772", "source_url": null, "captured_at": null, "author": null, "contributor": null}], "edges": [{"source": "docs_adr_adr_backlog_adr_backlog", "target": "docs_adr_adr_backlog_blocking_decisions", "relation": "references", "confidence": "EXTRACTED", "confidence_score": 1.0, "source_file": "docs/adr/adr-backlog.md", "source_location": null, "weight": 1.0}, {"source": "docs_adr_adr_backlog_adr_backlog", "target": "docs_adr_adr_backlog_deferred_decisions", "relation": "references", "confidence": "EXTRACTED", "confidence_score": 1.0, "source_file": "docs/adr/adr-backlog.md", "source_location": null, "weight": 1.0}, {"source": "docs_adr_adr_backlog_adr_backlog", "target": "docs_adr_adr_backlog_vertical_slice_prototype", "relation": "references", "confidence": "EXTRACTED", "confidence_score": 1.0, "source_file": "docs/adr/adr-backlog.md", "source_location": null, "weight": 1.0}, {"source": "docs_adr_adr_backlog_blocking_decisions", "target": "docs_adr_001_product_shape_and_operating_model_internal_hosted_web_app", "relation": "references", "confidence": "EXTRACTED", "confidence_score": 1.0, "source_file": "docs/adr/adr-backlog.md", "source_location": null, "weight": 1.0}, {"source": "docs_adr_adr_backlog_blocking_decisions", "target": "docs_adr_002_application_architecture_modular_monolith", "relation": "references", "confidence": "EXTRACTED", "confidence_score": 1.0, "source_file": "docs/adr/adr-backlog.md", "source_location": null, "weight": 1.0}, {"source": "docs_adr_adr_backlog_blocking_decisions", "target": "docs_adr_004_module_boundaries_and_business_rule_ownership_membership_rule_ownership", "relation": "references", "confidence": "EXTRACTED", "confidence_score": 1.0, "source_file": "docs/adr/adr-backlog.md", "source_location": null, "weight": 1.0}, {"source": "docs_adr_adr_backlog_blocking_decisions", "target": "docs_adr_005_membership_invariants_and_recalculation_hybrid_membership_model", "relation": "references", "confidence": "EXTRACTED", "confidence_score": 1.0, "source_file": "docs/adr/adr-backlog.md", "source_location": null, "weight": 1.0}, {"source": "docs_adr_adr_backlog_blocking_decisions", "target": "docs_adr_006_business_audit_corrections_and_technical_logs_append_only_business_audit", "relation": "references", "confidence": "EXTRACTED", "confidence_score": 1.0, "source_file": "docs/adr/adr-backlog.md", "source_location": null, "weight": 1.0}, {"source": "docs_adr_adr_backlog_blocking_decisions", "target": "docs_adr_008_search_identity_card_rules_and_duplicate_warnings_clients_search_identity", "relation": "references", "confidence": "EXTRACTED", "confidence_score": 1.0, "source_file": "docs/adr/adr-backlog.md", "source_location": null, "weight": 1.0}, {"source": "docs_adr_adr_backlog_blocking_decisions", "target": "docs_adr_011_membership_type_lifecycle_editable_catalog_immutable_snapshot", "relation": "references", "confidence": "EXTRACTED", "confidence_score": 1.0, "source_file": "docs/adr/adr-backlog.md", "source_location": null, "weight": 1.0}, {"source": "docs_adr_adr_backlog_blocking_decisions", "target": "docs_adr_012_permissions_session_accountability_and_corrections_owner_admin_shared_accounts", "relation": "references", "confidence": "EXTRACTED", "confidence_score": 1.0, "source_file": "docs/adr/adr-backlog.md", "source_location": null, "weight": 1.0}, {"source": "docs_adr_adr_backlog_deferred_decisions", "target": "docs_adr_009_backup_restore_and_operational_recovery_provider_managed_backups_restore_check", "relation": "references", "confidence": "EXTRACTED", "confidence_score": 1.0, "source_file": "docs/adr/adr-backlog.md", "source_location": null, "weight": 1.0}, {"source": "docs_adr_adr_backlog_deferred_decisions", "target": "docs_adr_010_migration_manual_backfill_and_paper_fallback_manual_backfill", "relation": "references", "confidence": "EXTRACTED", "confidence_score": 1.0, "source_file": "docs/adr/adr-backlog.md", "source_location": null, "weight": 1.0}, {"source": "docs_adr_adr_backlog_deferred_decisions", "target": "docs_adr_013_future_client_self_service_boundary_client_self_service_guardrail", "relation": "references", "confidence": "EXTRACTED", "confidence_score": 1.0, "source_file": "docs/adr/adr-backlog.md", "source_location": null, "weight": 1.0}, {"source": "docs_adr_adr_backlog_vertical_slice_prototype", "target": "docs_adr_003_ui_rendering_and_interaction_model_hybrid_server_rendered_ui", "relation": "references", "confidence": "EXTRACTED", "confidence_score": 1.0, "source_file": "docs/adr/adr-backlog.md", "source_location": null, "weight": 1.0}, {"source": "docs_adr_adr_backlog_vertical_slice_prototype", "target": "docs_adr_005_membership_invariants_and_recalculation_hybrid_membership_model", "relation": "references", "confidence": "EXTRACTED", "confidence_score": 1.0, "source_file": "docs/adr/adr-backlog.md", "source_location": null, "weight": 1.0}, {"source": "docs_adr_adr_backlog_vertical_slice_prototype", "target": "docs_adr_006_business_audit_corrections_and_technical_logs_append_only_business_audit", "relation": "references", "confidence": "EXTRACTED", "confidence_score": 1.0, "source_file": "docs/adr/adr-backlog.md", "source_location": null, "weight": 1.0}, {"source": "docs_adr_adr_backlog_vertical_slice_prototype", "target": "docs_adr_007_reporting_model_and_consistency_rules_reports_query_layer", "relation": "references", "confidence": "EXTRACTED", "confidence_score": 1.0, "source_file": "docs/adr/adr-backlog.md", "source_location": null, "weight": 1.0}, {"source": "docs_adr_adr_backlog_vertical_slice_prototype", "target": "docs_adr_008_search_identity_card_rules_and_duplicate_warnings_clients_search_identity", "relation": "references", "confidence": "EXTRACTED", "confidence_score": 1.0, "source_file": "docs/adr/adr-backlog.md", "source_location": null, "weight": 1.0}, {"source": "docs_adr_adr_backlog", "target": "docs_adr_adr_backlog_adr_backlog_bodylife_crm", "relation": "references", "confidence": "EXTRACTED", "confidence_score": 1.0, "source_file": "docs/adr/adr-backlog.md", "source_location": "L1", "weight": 1.0}, {"source": "docs_adr_adr_backlog", "target": "docs_adr_adr_backlog_section", "relation": "references", "confidence": "EXTRACTED", "confidence_score": 1.0, "source_file": "docs/adr/adr-backlog.md", "source_location": "L7", "weight": 1.0}, {"source": "docs_adr_adr_backlog", "target": "docs_adr_adr_backlog_section_2", "relation": "references", "confidence": "EXTRACTED", "confidence_score": 1.0, "source_file": "docs/adr/adr-backlog.md", "source_location": "L13", "weight": 1.0}, {"source": "docs_adr_adr_backlog", "target": "docs_adr_adr_backlog_section_3", "relation": "references", "confidence": "EXTRACTED", "confidence_score": 1.0, "source_file": "docs/adr/adr-backlog.md", "source_location": "L26", "weight": 1.0}, {"source": "docs_adr_adr_backlog", "target": "docs_adr_adr_backlog_vertical_slice_prototype_2", "relation": "references", "confidence": "EXTRACTED", "confidence_score": 1.0, "source_file": "docs/adr/adr-backlog.md", "source_location": "L35", "weight": 1.0}, {"source": "docs_adr_adr_backlog", "target": "docs_adr_adr_backlog_adr_001_product_shape_v1", "relation": "references", "confidence": "EXTRACTED", "confidence_score": 1.0, "source_file": "docs/adr/adr-backlog.md", "source_location": "L45", "weight": 1.0}, {"source": "docs_adr_adr_backlog", "target": "docs_adr_adr_backlog_adr_002_application_architecture", "relation": "references", "confidence": "EXTRACTED", "confidence_score": 1.0, "source_file": "docs/adr/adr-backlog.md", "source_location": "L82", "weight": 1.0}, {"source": "docs_adr_adr_backlog", "target": "docs_adr_adr_backlog_adr_003_ui_rendering_and_interaction_model", "relation": "references", "confidence": "EXTRACTED", "confidence_score": 1.0, "source_file": "docs/adr/adr-backlog.md", "source_location": "L128", "weight": 1.0}, {"source": "docs_adr_adr_backlog", "target": "docs_adr_adr_backlog_adr_004_module_boundaries_ownership", "relation": "references", "confidence": "EXTRACTED", "confidence_score": 1.0, "source_file": "docs/adr/adr-backlog.md", "source_location": "L171", "weight": 1.0}, {"source": "docs_adr_adr_backlog", "target": "docs_adr_adr_backlog_adr_005_membership_invariants", "relation": "references", "confidence": "EXTRACTED", "confidence_score": 1.0, "source_file": "docs/adr/adr-backlog.md", "source_location": "L239", "weight": 1.0}, {"source": "docs_adr_adr_backlog", "target": "docs_adr_adr_backlog_adr_006_business_audit_corrections_technical_logs", "relation": "references", "confidence": "EXTRACTED", "confidence_score": 1.0, "source_file": "docs/adr/adr-backlog.md", "source_location": "L287", "weight": 1.0}, {"source": "docs_adr_adr_backlog", "target": "docs_adr_adr_backlog_adr_007_reporting_model_consistency_rules", "relation": "references", "confidence": "EXTRACTED", "confidence_score": 1.0, "source_file": "docs/adr/adr-backlog.md", "source_location": "L334", "weight": 1.0}, {"source": "docs_adr_adr_backlog", "target": "docs_adr_adr_backlog_adr_008_search_identity_card_rules_duplicate_warnings", "relation": "references", "confidence": "EXTRACTED", "confidence_score": 1.0, "source_file": "docs/adr/adr-backlog.md", "source_location": "L397", "weight": 1.0}, {"source": "docs_adr_adr_backlog", "target": "docs_adr_adr_backlog_adr_009_backup_restore_operational_recovery", "relation": "references", "confidence": "EXTRACTED", "confidence_score": 1.0, "source_file": "docs/adr/adr-backlog.md", "source_location": "L465", "weight": 1.0}, {"source": "docs_adr_adr_backlog", "target": "docs_adr_adr_backlog_adr_010_migration_manual_backfill_paper_fallback_entries", "relation": "references", "confidence": "EXTRACTED", "confidence_score": 1.0, "source_file": "docs/adr/adr-backlog.md", "source_location": "L523", "weight": 1.0}, {"source": "docs_adr_adr_backlog", "target": "docs_adr_adr_backlog_adr_011_membership_type_lifecycle", "relation": "references", "confidence": "EXTRACTED", "confidence_score": 1.0, "source_file": "docs/adr/adr-backlog.md", "source_location": "L577", "weight": 1.0}, {"source": "docs_adr_adr_backlog", "target": "docs_adr_adr_backlog_adr_012_permissions_matrix_session_accountability", "relation": "references", "confidence": "EXTRACTED", "confidence_score": 1.0, "source_file": "docs/adr/adr-backlog.md", "source_location": "L636", "weight": 1.0}, {"source": "docs_adr_adr_backlog", "target": "docs_adr_adr_backlog_adr_013_future_client_self_service_boundary", "relation": "references", "confidence": "EXTRACTED", "confidence_score": 1.0, "source_file": "docs/adr/adr-backlog.md", "source_location": "L692", "weight": 1.0}, {"source": "docs_adr_adr_backlog", "target": "docs_adr_adr_backlog_section_4", "relation": "references", "confidence": "EXTRACTED", "confidence_score": 1.0, "source_file": "docs/adr/adr-backlog.md", "source_location": "L762", "weight": 1.0}, {"source": "docs_adr_adr_backlog", "target": "docs_adr_adr_backlog_vertical_slice_adr", "relation": "references", "confidence": "EXTRACTED", "confidence_score": 1.0, "source_file": "docs/adr/adr-backlog.md", "source_location": "L772", "weight": 1.0}, {"source": "docs_adr_adr_backlog", "target": "docs_adr_adr_backlog_adr_backlog", "relation": "references", "confidence": "INFERRED", "confidence_score": 0.85, "source_file": "docs/adr/adr-backlog.md", "source_location": null, "weight": 1.0}, {"source": "docs_adr_adr_backlog", "target": "docs_adr_adr_backlog_blocking_decisions", "relation": "references", "confidence": "INFERRED", "confidence_score": 0.85, "source_file": "docs/adr/adr-backlog.md", "source_location": null, "weight": 1.0}, {"source": "docs_adr_adr_backlog", "target": "docs_adr_adr_backlog_deferred_decisions", "relation": "references", "confidence": "INFERRED", "confidence_score": 0.85, "source_file": "docs/adr/adr-backlog.md", "source_location": null, "weight": 1.0}, {"source": "docs_adr_adr_backlog", "target": "docs_adr_adr_backlog_vertical_slice_prototype", "relation": "references", "confidence": "INFERRED", "confidence_score": 0.85, "source_file": "docs/adr/adr-backlog.md", "source_location": null, "weight": 1.0}], "hyperedges": [{"id": "reception_vertical_slice_risk_check", "label": "Reception Vertical Slice Risk Check", "nodes": ["docs_adr_003_ui_rendering_and_interaction_model_hybrid_server_rendered_ui", "docs_adr_005_membership_invariants_and_recalculation_hybrid_membership_model", "docs_adr_006_business_audit_corrections_and_technical_logs_append_only_business_audit", "docs_adr_007_reporting_model_and_consistency_rules_reports_query_layer", "docs_adr_008_search_identity_card_rules_and_duplicate_warnings_clients_search_identity"], "relation": "form", "confidence": "EXTRACTED", "confidence_score": 1.0, "source_file": "docs/adr/adr-backlog.md"}]}