{"nodes": [{"id": "agents_bodylife_crm_agent_instructions", "label": "BodyLife CRM Agent Instructions", "file_type": "document", "source_file": "AGENTS.md", "source_location": null, "source_url": null, "captured_at": null, "author": null, "contributor": null}, {"id": "agents_architecture_guardrails", "label": "Architecture Guardrails", "file_type": "rationale", "source_file": "AGENTS.md", "source_location": null, "source_url": null, "captured_at": null, "author": null, "contributor": null}, {"id": "agents_quality_gate_policy", "label": "Quality Gate Policy", "file_type": "concept", "source_file": "AGENTS.md", "source_location": null, "source_url": null, "captured_at": null, "author": null, "contributor": null}], "edges": [{"source": "agents_bodylife_crm_agent_instructions", "target": "docs_adr_readme_accepted_adr_package", "relation": "references", "confidence": "EXTRACTED", "confidence_score": 1.0, "source_file": "AGENTS.md", "source_location": null, "weight": 1.0}, {"source": "agents_bodylife_crm_agent_instructions", "target": "docs_implementation_roadmap_milestone_5_memberships", "relation": "references", "confidence": "EXTRACTED", "confidence_score": 1.0, "source_file": "AGENTS.md", "source_location": null, "weight": 1.0}, {"source": "agents_architecture_guardrails", "target": "docs_architecture_baseline_module_rule_ownership", "relation": "conceptually_related_to", "confidence": "INFERRED", "confidence_score": 0.95, "source_file": "AGENTS.md", "source_location": null, "weight": 1.0}, {"source": "agents_quality_gate_policy", "target": "docs_implementation_plan_validation_quality_gates", "relation": "conceptually_related_to", "confidence": "INFERRED", "confidence_score": 0.95, "source_file": "AGENTS.md", "source_location": null, "weight": 1.0}], "hyperedges": []}